setup.py
Netis.egg-info/PKG-INFO
Netis.egg-info/SOURCES.txt
Netis.egg-info/dependency_links.txt
Netis.egg-info/top_level.txt
netis/__init__.py
netis/source.py